UART_TX.v
module UART_TX#(parameter CLOCKS_PER_BIT = 217)(
    input i_Clk,
    input [7:0] i_TX_Byte,
    input i_TX_DV,
    output o_TX_Active,
    output o_TX_Serial,
    output o_TX_Done
);

parameter INITIAL = 3'b000;
parameter START_BIT = 3'b001;
parameter DATA_BITS = 3'b010;
parameter STOP_BIT = 3'b011;
parameter CLEANUP = 3'b100;

reg [2:0] r_State = INITIAL;
reg [7:0] r_Counter= 0;
reg [2:0] r_Bit_Index = 0;
reg [7:0] r_TX_Data = 0;
reg r_TX_Active = 0;
reg r_TX_Done = 0;
reg r_TX_Serial = 0;

always @(posedge i_Clk) begin
    case (r_State)
        INITIAL : begin
            r_TX_Serial <= 1'b1;
            r_TX_Done <= 1'b0;
            r_Counter <= 0;
            r_Bit_Index <= 0;

            if(i_TX_DV == 1'b1) begin
                r_State <= START_BIT;
                r_TX_Data <= i_TX_Byte;
                r_TX_Active <= 1'b1;
            end
            else begin
                r_State <= INITIAL;
            end
        end

        START_BIT : begin 
            if(r_Counter == CLOCKS_PER_BIT - 1) begin
                r_State <= DATA_BITS;
                r_Counter <= 0;
            end
            else begin
                r_Counter <= r_Counter + 1;
                r_TX_Serial <= 1'b0;
            end
        end

        DATA_BITS : begin 
            if(r_Bit_Index < 7) begin
                if(r_Counter == CLOCKS_PER_BIT - 1) begin
                    r_Counter <= 0;
                    r_Bit_Index <= r_Bit_Index + 1;
                end
                else begin
                    r_TX_Serial <= i_TX_Byte[r_Bit_Index];
                    r_Counter <= r_Counter + 1;
                end
            end
            else begin
                if(r_Counter == CLOCKS_PER_BIT - 1) begin
                    r_State <= STOP_BIT;
                    r_Counter <= 0;
                    r_Bit_Index <= 0;
                end
                else begin
                    r_TX_Serial <= i_TX_Byte[r_Bit_Index];
                    r_Counter <= r_Counter + 1;
                end
                
            end
        end

        STOP_BIT : begin
            if(r_Counter == CLOCKS_PER_BIT) begin
                r_State <= CLEANUP;
                r_Counter <= 0;
            end
            else begin
                r_Counter <= r_Counter + 1;
                r_TX_Serial <= 1'b1;
            end
        end

        CLEANUP : begin
            r_Counter <= 0;
            r_Bit_Index <= 0;
            r_State <= INITIAL;
            r_TX_Active <= 0;
            r_TX_Done <= 1'b1;
            r_TX_Data <= 0;
        end
    endcase
end

    assign o_TX_Serial = r_TX_Serial;
    assign o_TX_Done = r_TX_Done;
    assign o_TX_Active = r_TX_Active;

endmodule

UART_RX.v
module UART_RX #(parameter CLOCKS_PER_BIT = 217) (
    input i_Clk,
    input i_RX_Serial,
    output o_RX_DV,
    output [7:0] o_RX_Byte
);

    // enum states
    parameter INITIAL  = 3'b000;
    parameter START_BIT = 3'b001;
    parameter SERIAL_DATA = 3'b010;
    parameter STOP_BIT = 3'b011;
    parameter CLEANUP = 3'b100;

    reg [2:0] r_State = 3'b000;
    reg [7:0] r_RX_Byte = 3'b000;
    reg r_RX_DV = 0;
    reg [2:0] r_Bit_Index = 0;
    reg [7:0] r_Clock_Count = 0;

    always @(posedge i_Clk) begin
        case (r_State) 
            INITIAL :
                begin
                    r_RX_DV <= 0;
                    r_Clock_Count <= 0;
                    r_Bit_Index <= 0;

                    if(i_RX_Serial == 1'b0) 
                        begin
                            r_State <= START_BIT;
                        end
                    else
                        begin
                            r_State <= INITIAL;
                        end
                end
            START_BIT :
                begin
                    if(r_Clock_Count == (CLOCKS_PER_BIT - 1) / 2)
                        begin
                            if(i_RX_Serial == 1'b0)
                                begin
                                    r_State <= SERIAL_DATA;
                                end
                            else
                                begin
                                    r_State <= INITIAL;
                                end
                            r_Clock_Count <= 0;    
                        end
                    else 
                        begin
                            r_Clock_Count <= r_Clock_Count + 1;
                        end
                    
                end
            SERIAL_DATA :
                begin
                    if(r_Clock_Count == CLOCKS_PER_BIT - 1)
                        begin
                            if(r_Bit_Index < 7)
                                begin
                                    r_RX_Byte[r_Bit_Index] <= i_RX_Serial;
                                    r_Bit_Index <= r_Bit_Index + 1;
                                    r_Clock_Count <= 0;
                                end
                            else
                                begin
                                    r_RX_Byte[r_Bit_Index] <= i_RX_Serial;
                                    r_State <= STOP_BIT;
                                    r_Bit_Index <= 0;
                                    r_Clock_Count <= 0;
                                end 
                        end
                    else
                        begin
                            r_Clock_Count <= r_Clock_Count + 1;
                        end
                end
            STOP_BIT :
                begin
                    if(r_Clock_Count == CLOCKS_PER_BIT - 1)
                        begin
                            r_State <= CLEANUP;
                            r_Clock_Count <= 0;
                        end
                    else
                        begin
                            r_Clock_Count <= r_Clock_Count + 1;
                        end
                end
            CLEANUP :
                begin
                    r_RX_DV <= 1'b1;
                    r_Clock_Count <= 0;
                    r_State <= INITIAL;
                    r_Bit_Index <= 0;
                end
            default : r_State <= INITIAL;
        endcase
    end 

    assign o_RX_Byte = r_RX_Byte;
    assign o_RX_DV = r_RX_DV;
    
endmodule

UART_TX_TB.v
`timescale 1ps/1ps
`include "UART_TX.v"
`include "UART_RX.v"

module UART_TX_TB();

    parameter c_CLOCK_PERIOD_NS = 40;
    parameter c_CLOCKS_PER_BIT = 217;
    parameter c_BIT_PERIOD = 8680;

    reg r_Clock = 0;
    reg r_TX_DV = 0;
    reg [7:0] r_TX_Byte = 0;
    wire w_TX_Serial;
    wire w_TX_Active;
    wire w_UART_Line;
    wire [7:0] w_RX_Byte;
    wire w_RX_DV;

    UART_RX #(c_CLOCKS_PER_BIT) RX_Inst (
        .i_Clk(r_Clock),
        .i_RX_Serial(w_UART_Line),
        .o_RX_DV(w_RX_DV),
        .o_RX_Byte(w_RX_Byte)
    );

    UART_TX #(c_CLOCKS_PER_BIT) TX_Inst (
        .i_Clk(r_Clock),
        .i_TX_Byte(r_TX_Byte),
        .i_TX_DV(r_TX_DV),
        .o_TX_Active(w_TX_Active),
        .o_TX_Serial(w_TX_Serial),
        .o_TX_Done()
    );

    assign w_UART_Line = w_TX_Active ? w_TX_Serial : 1'b1;

    always begin
        #(c_CLOCK_PERIOD_NS / 2) r_Clock <= !r_Clock;
    end

    initial begin
        @(posedge r_Clock);
        @(posedge r_Clock);
        r_TX_DV <= 1'b1;
        r_TX_Byte <= 8'h37;
        @(posedge r_Clock);
        r_TX_DV <= 1'b0;

        @(posedge r_Clock);
        #10000000
        @(posedge r_Clock);
        if(w_RX_Byte == 8'h37) begin
            $display("Test passed...");
        end
        else begin
            $display("Test failed...");
        end
        $finish();

    end

    initial begin
        $dumpfile("TX_TB.vcd");
        $dumpvars(0);
    end



endmodule

TX_TB.vcd
$date
	Sat Jul 30 22:55:00 2022
$end
$version
	Icarus Verilog
$end
$timescale
	1ps
$end
$scope module UART_TX_TB $end
$var wire 1 ! w_UART_Line $end
$var wire 1 " w_TX_Serial $end
$var wire 1 # w_TX_Active $end
$var wire 1 $ w_RX_DV $end
$var wire 8 % w_RX_Byte [7:0] $end
$var parameter 32 & c_BIT_PERIOD $end
$var parameter 32 ' c_CLOCKS_PER_BIT $end
$var parameter 32 ( c_CLOCK_PERIOD_NS $end
$var reg 1 ) r_Clock $end
$var reg 8 * r_TX_Byte [7:0] $end
$var reg 1 + r_TX_DV $end
$scope module RX_Inst $end
$var wire 1 ) i_Clk $end
$var wire 1 ! i_RX_Serial $end
$var wire 8 , o_RX_Byte [7:0] $end
$var wire 1 $ o_RX_DV $end
$var parameter 3 - CLEANUP $end
$var parameter 32 . CLOCKS_PER_BIT $end
$var parameter 3 / INITIAL $end
$var parameter 3 0 SERIAL_DATA $end
$var parameter 3 1 START_BIT $end
$var parameter 3 2 STOP_BIT $end
$var reg 3 3 r_Bit_Index [2:0] $end
$var reg 8 4 r_Clock_Count [7:0] $end
$var reg 8 5 r_RX_Byte [7:0] $end
$var reg 1 6 r_RX_DV $end
$var reg 3 7 r_State [2:0] $end
$upscope $end
$scope module TX_Inst $end
$var wire 1 ) i_Clk $end
$var wire 8 8 i_TX_Byte [7:0] $end
$var wire 1 + i_TX_DV $end
$var wire 1 9 o_TX_Done $end
$var wire 1 " o_TX_Serial $end
$var wire 1 # o_TX_Active $end
$var parameter 3 : CLEANUP $end
$var parameter 32 ; CLOCKS_PER_BIT $end
$var parameter 3 < DATA_BITS $end
$var parameter 3 = INITIAL $end
$var parameter 3 > START_BIT $end
$var parameter 3 ? STOP_BIT $end
$var reg 3 @ r_Bit_Index [2:0] $end
$var reg 8 A r_Counter [7:0] $end
$var reg 3 B r_State [2:0] $end
$var reg 1 # r_TX_Active $end
$var reg 8 C r_TX_Data [7:0] $end
$var reg 1 D r_TX_Done $end
$var reg 1 " r_TX_Serial $end
$upscope $end
$upscope $end
$enddefinitions $end
$comment Show the parameter values. $end
$dumpall
b11 ?
b1 >
b0 =
b10 <
b11011001 ;
b100 :
b11 2
b1 1
b10 0
b0 /
b11011001 .
b100 -
b101000 (
b11011001 '
b10000111101000 &
$end
#0
$dumpvars
0D
b0 C
b0 B
b0 A
b0 @
09
b0 8
b0 7
06
b0 5
b0 4
b0 3
b0 ,
0+
b0 *
0)
b0 %
0$
0#
0"
1!
$end
#20
1"
1)
#40
0)
#60
b110111 *
b110111 8
1+
1)
#80
0)
#100
1#
b110111 C
b1 B
0+
1)
#120
0)
#140
0!
0"
b1 A
1)
#160
0)
#180
b1 7
b10 A
1)
#200
0)
#220
b11 A
b1 4
1)
#240
0)
#260
b10 4
b100 A
1)
#280
0)
#300
b101 A
b11 4
1)
#320
0)
#340
b100 4
b110 A
1)
#360
0)
#380
b111 A
b101 4
1)
#400
0)
#420
b110 4
b1000 A
1)
#440
0)
#460
b1001 A
b111 4
1)
#480
0)
#500
b1000 4
b1010 A
1)
#520
0)
#540
b1011 A
b1001 4
1)
#560
0)
#580
b1010 4
b1100 A
1)
#600
0)
#620
b1101 A
b1011 4
1)
#640
0)
#660
b1100 4
b1110 A
1)
#680
0)
#700
b1111 A
b1101 4
1)
#720
0)
#740
b1110 4
b10000 A
1)
#760
0)
#780
b10001 A
b1111 4
1)
#800
0)
#820
b10000 4
b10010 A
1)
#840
0)
#860
b10011 A
b10001 4
1)
#880
0)
#900
b10010 4
b10100 A
1)
#920
0)
#940
b10101 A
b10011 4
1)
#960
0)
#980
b10100 4
b10110 A
1)
#1000
0)
#1020
b10111 A
b10101 4
1)
#1040
0)
#1060
b10110 4
b11000 A
1)
#1080
0)
#1100
b11001 A
b10111 4
1)
#1120
0)
#1140
b11000 4
b11010 A
1)
#1160
0)
#1180
b11011 A
b11001 4
1)
#1200
0)
#1220
b11010 4
b11100 A
1)
#1240
0)
#1260
b11101 A
b11011 4
1)
#1280
0)
#1300
b11100 4
b11110 A
1)
#1320
0)
#1340
b11111 A
b11101 4
1)
#1360
0)
#1380
b11110 4
b100000 A
1)
#1400
0)
#1420
b100001 A
b11111 4
1)
#1440
0)
#1460
b100000 4
b100010 A
1)
#1480
0)
#1500
b100011 A
b100001 4
1)
#1520
0)
#1540
b100010 4
b100100 A
1)
#1560
0)
#1580
b100101 A
b100011 4
1)
#1600
0)
#1620
b100100 4
b100110 A
1)
#1640
0)
#1660
b100111 A
b100101 4
1)
#1680
0)
#1700
b100110 4
b101000 A
1)
#1720
0)
#1740
b101001 A
b100111 4
1)
#1760
0)
#1780
b101000 4
b101010 A
1)
#1800
0)
#1820
b101011 A
b101001 4
1)
#1840
0)
#1860
b101010 4
b101100 A
1)
#1880
0)
#1900
b101101 A
b101011 4
1)
#1920
0)
#1940
b101100 4
b101110 A
1)
#1960
0)
#1980
b101111 A
b101101 4
1)
#2000
0)
#2020
b101110 4
b110000 A
1)
#2040
0)
#2060
b110001 A
b101111 4
1)
#2080
0)
#2100
b110000 4
b110010 A
1)
#2120
0)
#2140
b110011 A
b110001 4
1)
#2160
0)
#2180
b110010 4
b110100 A
1)
#2200
0)
#2220
b110101 A
b110011 4
1)
#2240
0)
#2260
b110100 4
b110110 A
1)
#2280
0)
#2300
b110111 A
b110101 4
1)
#2320
0)
#2340
b110110 4
b111000 A
1)
#2360
0)
#2380
b111001 A
b110111 4
1)
#2400
0)
#2420
b111000 4
b111010 A
1)
#2440
0)
#2460
b111011 A
b111001 4
1)
#2480
0)
#2500
b111010 4
b111100 A
1)
#2520
0)
#2540
b111101 A
b111011 4
1)
#2560
0)
#2580
b111100 4
b111110 A
1)
#2600
0)
#2620
b111111 A
b111101 4
1)
#2640
0)
#2660
b111110 4
b1000000 A
1)
#2680
0)
#2700
b1000001 A
b111111 4
1)
#2720
0)
#2740
b1000000 4
b1000010 A
1)
#2760
0)
#2780
b1000011 A
b1000001 4
1)
#2800
0)
#2820
b1000010 4
b1000100 A
1)
#2840
0)
#2860
b1000101 A
b1000011 4
1)
#2880
0)
#2900
b1000100 4
b1000110 A
1)
#2920
0)
#2940
b1000111 A
b1000101 4
1)
#2960
0)
#2980
b1000110 4
b1001000 A
1)
#3000
0)
#3020
b1001001 A
b1000111 4
1)
#3040
0)
#3060
b1001000 4
b1001010 A
1)
#3080
0)
#3100
b1001011 A
b1001001 4
1)
#3120
0)
#3140
b1001010 4
b1001100 A
1)
#3160
0)
#3180
b1001101 A
b1001011 4
1)
#3200
0)
#3220
b1001100 4
b1001110 A
1)
#3240
0)
#3260
b1001111 A
b1001101 4
1)
#3280
0)
#3300
b1001110 4
b1010000 A
1)
#3320
0)
#3340
b1010001 A
b1001111 4
1)
#3360
0)
#3380
b1010000 4
b1010010 A
1)
#3400
0)
#3420
b1010011 A
b1010001 4
1)
#3440
0)
#3460
b1010010 4
b1010100 A
1)
#3480
0)
#3500
b1010101 A
b1010011 4
1)
#3520
0)
#3540
b1010100 4
b1010110 A
1)
#3560
0)
#3580
b1010111 A
b1010101 4
1)
#3600
0)
#3620
b1010110 4
b1011000 A
1)
#3640
0)
#3660
b1011001 A
b1010111 4
1)
#3680
0)
#3700
b1011000 4
b1011010 A
1)
#3720
0)
#3740
b1011011 A
b1011001 4
1)
#3760
0)
#3780
b1011010 4
b1011100 A
1)
#3800
0)
#3820
b1011101 A
b1011011 4
1)
#3840
0)
#3860
b1011100 4
b1011110 A
1)
#3880
0)
#3900
b1011111 A
b1011101 4
1)
#3920
0)
#3940
b1011110 4
b1100000 A
1)
#3960
0)
#3980
b1100001 A
b1011111 4
1)
#4000
0)
#4020
b1100000 4
b1100010 A
1)
#4040
0)
#4060
b1100011 A
b1100001 4
1)
#4080
0)
#4100
b1100010 4
b1100100 A
1)
#4120
0)
#4140
b1100101 A
b1100011 4
1)
#4160
0)
#4180
b1100100 4
b1100110 A
1)
#4200
0)
#4220
b1100111 A
b1100101 4
1)
#4240
0)
#4260
b1100110 4
b1101000 A
1)
#4280
0)
#4300
b1101001 A
b1100111 4
1)
#4320
0)
#4340
b1101000 4
b1101010 A
1)
#4360
0)
#4380
b1101011 A
b1101001 4
1)
#4400
0)
#4420
b1101010 4
b1101100 A
1)
#4440
0)
#4460
b1101101 A
b1101011 4
1)
#4480
0)
#4500
b1101100 4
b1101110 A
1)
#4520
0)
#4540
b1101111 A
b0 4
b10 7
1)
#4560
0)
#4580
b1 4
b1110000 A
1)
#4600
0)
#4620
b1110001 A
b10 4
1)
#4640
0)
#4660
b11 4
b1110010 A
1)
#4680
0)
#4700
b1110011 A
b100 4
1)
#4720
0)
#4740
b101 4
b1110100 A
1)
#4760
0)
#4780
b1110101 A
b110 4
1)
#4800
0)
#4820
b111 4
b1110110 A
1)
#4840
0)
#4860
b1110111 A
b1000 4
1)
#4880
0)
#4900
b1001 4
b1111000 A
1)
#4920
0)
#4940
b1111001 A
b1010 4
1)
#4960
0)
#4980
b1011 4
b1111010 A
1)
#5000
0)
#5020
b1111011 A
b1100 4
1)
#5040
0)
#5060
b1101 4
b1111100 A
1)
#5080
0)
#5100
b1111101 A
b1110 4
1)
#5120
0)
#5140
b1111 4
b1111110 A
1)
#5160
0)
#5180
b1111111 A
b10000 4
1)
#5200
0)
#5220
b10001 4
b10000000 A
1)
#5240
0)
#5260
b10000001 A
b10010 4
1)
#5280
0)
#5300
b10011 4
b10000010 A
1)
#5320
0)
#5340
b10000011 A
b10100 4
1)
#5360
0)
#5380
b10101 4
b10000100 A
1)
#5400
0)
#5420
b10000101 A
b10110 4
1)
#5440
0)
#5460
b10111 4
b10000110 A
1)
#5480
0)
#5500
b10000111 A
b11000 4
1)
#5520
0)
#5540
b11001 4
b10001000 A
1)
#5560
0)
#5580
b10001001 A
b11010 4
1)
#5600
0)
#5620
b11011 4
b10001010 A
1)
#5640
0)
#5660
b10001011 A
b11100 4
1)
#5680
0)
#5700
b11101 4
b10001100 A
1)
#5720
0)
#5740
b10001101 A
b11110 4
1)
#5760
0)
#5780
b11111 4
b10001110 A
1)
#5800
0)
#5820
b10001111 A
b100000 4
1)
#5840
0)
#5860
b100001 4
b10010000 A
1)
#5880
0)
#5900
b10010001 A
b100010 4
1)
#5920
0)
#5940
b100011 4
b10010010 A
1)
#5960
0)
#5980
b10010011 A
b100100 4
1)
#6000
0)
#6020
b100101 4
b10010100 A
1)
#6040
0)
#6060
b10010101 A
b100110 4
1)
#6080
0)
#6100
b100111 4
b10010110 A
1)
#6120
0)
#6140
b10010111 A
b101000 4
1)
#6160
0)
#6180
b101001 4
b10011000 A
1)
#6200
0)
#6220
b10011001 A
b101010 4
1)
#6240
0)
#6260
b101011 4
b10011010 A
1)
#6280
0)
#6300
b10011011 A
b101100 4
1)
#6320
0)
#6340
b101101 4
b10011100 A
1)
#6360
0)
#6380
b10011101 A
b101110 4
1)
#6400
0)
#6420
b101111 4
b10011110 A
1)
#6440
0)
#6460
b10011111 A
b110000 4
1)
#6480
0)
#6500
b110001 4
b10100000 A
1)
#6520
0)
#6540
b10100001 A
b110010 4
1)
#6560
0)
#6580
b110011 4
b10100010 A
1)
#6600
0)
#6620
b10100011 A
b110100 4
1)
#6640
0)
#6660
b110101 4
b10100100 A
1)
#6680
0)
#6700
b10100101 A
b110110 4
1)
#6720
0)
#6740
b110111 4
b10100110 A
1)
#6760
0)
#6780
b10100111 A
b111000 4
1)
#6800
0)
#6820
b111001 4
b10101000 A
1)
#6840
0)
#6860
b10101001 A
b111010 4
1)
#6880
0)
#6900
b111011 4
b10101010 A
1)
#6920
0)
#6940
b10101011 A
b111100 4
1)
#6960
0)
#6980
b111101 4
b10101100 A
1)
#7000
0)
#7020
b10101101 A
b111110 4
1)
#7040
0)
#7060
b111111 4
b10101110 A
1)
#7080
0)
#7100
b10101111 A
b1000000 4
1)
#7120
0)
#7140
b1000001 4
b10110000 A
1)
#7160
0)
#7180
b10110001 A
b1000010 4
1)
#7200
0)
#7220
b1000011 4
b10110010 A
1)
#7240
0)
#7260
b10110011 A
b1000100 4
1)
#7280
0)
#7300
b1000101 4
b10110100 A
1)
#7320
0)
#7340
b10110101 A
b1000110 4
1)
#7360
0)
#7380
b1000111 4
b10110110 A
1)
#7400
0)
#7420
b10110111 A
b1001000 4
1)
#7440
0)
#7460
b1001001 4
b10111000 A
1)
#7480
0)
#7500
b10111001 A
b1001010 4
1)
#7520
0)
#7540
b1001011 4
b10111010 A
1)
#7560
0)
#7580
b10111011 A
b1001100 4
1)
#7600
0)
#7620
b1001101 4
b10111100 A
1)
#7640
0)
#7660
b10111101 A
b1001110 4
1)
#7680
0)
#7700
b1001111 4
b10111110 A
1)
#7720
0)
#7740
b10111111 A
b1010000 4
1)
#7760
0)
#7780
b1010001 4
b11000000 A
1)
#7800
0)
#7820
b11000001 A
b1010010 4
1)
#7840
0)
#7860
b1010011 4
b11000010 A
1)
#7880
0)
#7900
b11000011 A
b1010100 4
1)
#7920
0)
#7940
b1010101 4
b11000100 A
1)
#7960
0)
#7980
b11000101 A
b1010110 4
1)
#8000
0)
#8020
b1010111 4
b11000110 A
1)
#8040
0)
#8060
b11000111 A
b1011000 4
1)
#8080
0)
#8100
b1011001 4
b11001000 A
1)
#8120
0)
#8140
b11001001 A
b1011010 4
1)
#8160
0)
#8180
b1011011 4
b11001010 A
1)
#8200
0)
#8220
b11001011 A
b1011100 4
1)
#8240
0)
#8260
b1011101 4
b11001100 A
1)
#8280
0)
#8300
b11001101 A
b1011110 4
1)
#8320
0)
#8340
b1011111 4
b11001110 A
1)
#8360
0)
#8380
b11001111 A
b1100000 4
1)
#8400
0)
#8420
b1100001 4
b11010000 A
1)
#8440
0)
#8460
b11010001 A
b1100010 4
1)
#8480
0)
#8500
b1100011 4
b11010010 A
1)
#8520
0)
#8540
b11010011 A
b1100100 4
1)
#8560
0)
#8580
b1100101 4
b11010100 A
1)
#8600
0)
#8620
b11010101 A
b1100110 4
1)
#8640
0)
#8660
b1100111 4
b11010110 A
1)
#8680
0)
#8700
b11010111 A
b1101000 4
1)
#8720
0)
#8740
b1101001 4
b11011000 A
1)
#8760
0)
#8780
b0 A
b10 B
b1101010 4
1)
#8800
0)
#8820
1!
b1101011 4
b1 A
1"
1)
#8840
0)
#8860
b10 A
b1101100 4
1)
#8880
0)
#8900
b1101101 4
b11 A
1)
#8920
0)
#8940
b100 A
b1101110 4
1)
#8960
0)
#8980
b1101111 4
b101 A
1)
#9000
0)
#9020
b110 A
b1110000 4
1)
#9040
0)
#9060
b1110001 4
b111 A
1)
#9080
0)
#9100
b1000 A
b1110010 4
1)
#9120
0)
#9140
b1110011 4
b1001 A
1)
#9160
0)
#9180
b1010 A
b1110100 4
1)
#9200
0)
#9220
b1110101 4
b1011 A
1)
#9240
0)
#9260
b1100 A
b1110110 4
1)
#9280
0)
#9300
b1110111 4
b1101 A
1)
#9320
0)
#9340
b1110 A
b1111000 4
1)
#9360
0)
#9380
b1111001 4
b1111 A
1)
#9400
0)
#9420
b10000 A
b1111010 4
1)
#9440
0)
#9460
b1111011 4
b10001 A
1)
#9480
0)
#9500
b10010 A
b1111100 4
1)
#9520
0)
#9540
b1111101 4
b10011 A
1)
#9560
0)
#9580
b10100 A
b1111110 4
1)
#9600
0)
#9620
b1111111 4
b10101 A
1)
#9640
0)
#9660
b10110 A
b10000000 4
1)
#9680
0)
#9700
b10000001 4
b10111 A
1)
#9720
0)
#9740
b11000 A
b10000010 4
1)
#9760
0)
#9780
b10000011 4
b11001 A
1)
#9800
0)
#9820
b11010 A
b10000100 4
1)
#9840
0)
#9860
b10000101 4
b11011 A
1)
#9880
0)
#9900
b11100 A
b10000110 4
1)
#9920
0)
#9940
b10000111 4
b11101 A
1)
#9960
0)
#9980
b11110 A
b10001000 4
1)
#10000
0)
#10020
b10001001 4
b11111 A
1)
#10040
0)
#10060
b100000 A
b10001010 4
1)
#10080
0)
#10100
b10001011 4
b100001 A
1)
#10120
0)
#10140
b100010 A
b10001100 4
1)
#10160
0)
#10180
b10001101 4
b100011 A
1)
#10200
0)
#10220
b100100 A
b10001110 4
1)
#10240
0)
#10260
b10001111 4
b100101 A
1)
#10280
0)
#10300
b100110 A
b10010000 4
1)
#10320
0)
#10340
b10010001 4
b100111 A
1)
#10360
0)
#10380
b101000 A
b10010010 4
1)
#10400
0)
#10420
b10010011 4
b101001 A
1)
#10440
0)
#10460
b101010 A
b10010100 4
1)
#10480
0)
#10500
b10010101 4
b101011 A
1)
#10520
0)
#10540
b101100 A
b10010110 4
1)
#10560
0)
#10580
b10010111 4
b101101 A
1)
#10600
0)
#10620
b101110 A
b10011000 4
1)
#10640
0)
#10660
b10011001 4
b101111 A
1)
#10680
0)
#10700
b110000 A
b10011010 4
1)
#10720
0)
#10740
b10011011 4
b110001 A
1)
#10760
0)
#10780
b110010 A
b10011100 4
1)
#10800
0)
#10820
b10011101 4
b110011 A
1)
#10840
0)
#10860
b110100 A
b10011110 4
1)
#10880
0)
#10900
b10011111 4
b110101 A
1)
#10920
0)
#10940
b110110 A
b10100000 4
1)
#10960
0)
#10980
b10100001 4
b110111 A
1)
#11000
0)
#11020
b111000 A
b10100010 4
1)
#11040
0)
#11060
b10100011 4
b111001 A
1)
#11080
0)
#11100
b111010 A
b10100100 4
1)
#11120
0)
#11140
b10100101 4
b111011 A
1)
#11160
0)
#11180
b111100 A
b10100110 4
1)
#11200
0)
#11220
b10100111 4
b111101 A
1)
#11240
0)
#11260
b111110 A
b10101000 4
1)
#11280
0)
#11300
b10101001 4
b111111 A
1)
#11320
0)
#11340
b1000000 A
b10101010 4
1)
#11360
0)
#11380
b10101011 4
b1000001 A
1)
#11400
0)
#11420
b1000010 A
b10101100 4
1)
#11440
0)
#11460
b10101101 4
b1000011 A
1)
#11480
0)
#11500
b1000100 A
b10101110 4
1)
#11520
0)
#11540
b10101111 4
b1000101 A
1)
#11560
0)
#11580
b1000110 A
b10110000 4
1)
#11600
0)
#11620
b10110001 4
b1000111 A
1)
#11640
0)
#11660
b1001000 A
b10110010 4
1)
#11680
0)
#11700
b10110011 4
b1001001 A
1)
#11720
0)
#11740
b1001010 A
b10110100 4
1)
#11760
0)
#11780
b10110101 4
b1001011 A
1)
#11800
0)
#11820
b1001100 A
b10110110 4
1)
#11840
0)
#11860
b10110111 4
b1001101 A
1)
#11880
0)
#11900
b1001110 A
b10111000 4
1)
#11920
0)
#11940
b10111001 4
b1001111 A
1)
#11960
0)
#11980
b1010000 A
b10111010 4
1)
#12000
0)
#12020
b10111011 4
b1010001 A
1)
#12040
0)
#12060
b1010010 A
b10111100 4
1)
#12080
0)
#12100
b10111101 4
b1010011 A
1)
#12120
0)
#12140
b1010100 A
b10111110 4
1)
#12160
0)
#12180
b10111111 4
b1010101 A
1)
#12200
0)
#12220
b1010110 A
b11000000 4
1)
#12240
0)
#12260
b11000001 4
b1010111 A
1)
#12280
0)
#12300
b1011000 A
b11000010 4
1)
#12320
0)
#12340
b11000011 4
b1011001 A
1)
#12360
0)
#12380
b1011010 A
b11000100 4
1)
#12400
0)
#12420
b11000101 4
b1011011 A
1)
#12440
0)
#12460
b1011100 A
b11000110 4
1)
#12480
0)
#12500
b11000111 4
b1011101 A
1)
#12520
0)
#12540
b1011110 A
b11001000 4
1)
#12560
0)
#12580
b11001001 4
b1011111 A
1)
#12600
0)
#12620
b1100000 A
b11001010 4
1)
#12640
0)
#12660
b11001011 4
b1100001 A
1)
#12680
0)
#12700
b1100010 A
b11001100 4
1)
#12720
0)
#12740
b11001101 4
b1100011 A
1)
#12760
0)
#12780
b1100100 A
b11001110 4
1)
#12800
0)
#12820
b11001111 4
b1100101 A
1)
#12840
0)
#12860
b1100110 A
b11010000 4
1)
#12880
0)
#12900
b11010001 4
b1100111 A
1)
#12920
0)
#12940
b1101000 A
b11010010 4
1)
#12960
0)
#12980
b11010011 4
b1101001 A
1)
#13000
0)
#13020
b1101010 A
b11010100 4
1)
#13040
0)
#13060
b11010101 4
b1101011 A
1)
#13080
0)
#13100
b1101100 A
b11010110 4
1)
#13120
0)
#13140
b11010111 4
b1101101 A
1)
#13160
0)
#13180
b1101110 A
b11011000 4
1)
#13200
0)
#13220
b0 4
b1 3
b1 %
b1 ,
b1 5
b1101111 A
1)
#13240
0)
#13260
b1110000 A
b1 4
1)
#13280
0)
#13300
b10 4
b1110001 A
1)
#13320
0)
#13340
b1110010 A
b11 4
1)
#13360
0)
#13380
b100 4
b1110011 A
1)
#13400
0)
#13420
b1110100 A
b101 4
1)
#13440
0)
#13460
b110 4
b1110101 A
1)
#13480
0)
#13500
b1110110 A
b111 4
1)
#13520
0)
#13540
b1000 4
b1110111 A
1)
#13560
0)
#13580
b1111000 A
b1001 4
1)
#13600
0)
#13620
b1010 4
b1111001 A
1)
#13640
0)
#13660
b1111010 A
b1011 4
1)
#13680
0)
#13700
b1100 4
b1111011 A
1)
#13720
0)
#13740
b1111100 A
b1101 4
1)
#13760
0)
#13780
b1110 4
b1111101 A
1)
#13800
0)
#13820
b1111110 A
b1111 4
1)
#13840
0)
#13860
b10000 4
b1111111 A
1)
#13880
0)
#13900
b10000000 A
b10001 4
1)
#13920
0)
#13940
b10010 4
b10000001 A
1)
#13960
0)
#13980
b10000010 A
b10011 4
1)
#14000
0)
#14020
b10100 4
b10000011 A
1)
#14040
0)
#14060
b10000100 A
b10101 4
1)
#14080
0)
#14100
b10110 4
b10000101 A
1)
#14120
0)
#14140
b10000110 A
b10111 4
1)
#14160
0)
#14180
b11000 4
b10000111 A
1)
#14200
0)
#14220
b10001000 A
b11001 4
1)
#14240
0)
#14260
b11010 4
b10001001 A
1)
#14280
0)
#14300
b10001010 A
b11011 4
1)
#14320
0)
#14340
b11100 4
b10001011 A
1)
#14360
0)
#14380
b10001100 A
b11101 4
1)
#14400
0)
#14420
b11110 4
b10001101 A
1)
#14440
0)
#14460
b10001110 A
b11111 4
1)
#14480
0)
#14500
b100000 4
b10001111 A
1)
#14520
0)
#14540
b10010000 A
b100001 4
1)
#14560
0)
#14580
b100010 4
b10010001 A
1)
#14600
0)
#14620
b10010010 A
b100011 4
1)
#14640
0)
#14660
b100100 4
b10010011 A
1)
#14680
0)
#14700
b10010100 A
b100101 4
1)
#14720
0)
#14740
b100110 4
b10010101 A
1)
#14760
0)
#14780
b10010110 A
b100111 4
1)
#14800
0)
#14820
b101000 4
b10010111 A
1)
#14840
0)
#14860
b10011000 A
b101001 4
1)
#14880
0)
#14900
b101010 4
b10011001 A
1)
#14920
0)
#14940
b10011010 A
b101011 4
1)
#14960
0)
#14980
b101100 4
b10011011 A
1)
#15000
0)
#15020
b10011100 A
b101101 4
1)
#15040
0)
#15060
b101110 4
b10011101 A
1)
#15080
0)
#15100
b10011110 A
b101111 4
1)
#15120
0)
#15140
b110000 4
b10011111 A
1)
#15160
0)
#15180
b10100000 A
b110001 4
1)
#15200
0)
#15220
b110010 4
b10100001 A
1)
#15240
0)
#15260
b10100010 A
b110011 4
1)
#15280
0)
#15300
b110100 4
b10100011 A
1)
#15320
0)
#15340
b10100100 A
b110101 4
1)
#15360
0)
#15380
b110110 4
b10100101 A
1)
#15400
0)
#15420
b10100110 A
b110111 4
1)
#15440
0)
#15460
b111000 4
b10100111 A
1)
#15480
0)
